.gitignore
LICENSE.txt
MANIFEST.in
README.md
setup.py
cmsplugin_instagram/__init__.py
cmsplugin_instagram/cms_plugins.py
cmsplugin_instagram/models.py
cmsplugin_instagram.egg-info/PKG-INFO
cmsplugin_instagram.egg-info/SOURCES.txt
cmsplugin_instagram.egg-info/dependency_links.txt
cmsplugin_instagram.egg-info/requires.txt
cmsplugin_instagram.egg-info/top_level.txt
cmsplugin_instagram/locale/de/LC_MESSAGES/django.mo
cmsplugin_instagram/locale/de/LC_MESSAGES/django.po
cmsplugin_instagram/migrations/0001_initial.py
cmsplugin_instagram/migrations/__init__.py
cmsplugin_instagram/migrations_django/0001_initial.py
cmsplugin_instagram/migrations_django/__init__.py
cmsplugin_instagram/static/cmsplugin_instagram/styles.css
cmsplugin_instagram/templates/cmsplugin_instagram/_instagram_plugin.html