Metadata-Version: 1.1
Name: cmsplugin-instagram
Version: 0.0.12
Summary: A djangocms plugin displaying images of an instagram account
Home-page: https://github.com/creimers/cmsplugin_instagram
Author: Christoph Reimers
Author-email: christoph@superservice-international.com
License: BSD License
Keywords: djangocms,django,instagram
Platform: UNKNOWN
Classifier: Operating System :: OS Independent
Classifier: Development Status :: 4 - Beta
Classifier: Programming Language :: Python
Classifier: Framework :: Django
Classifier: Programming Language :: Python :: 2.7
Classifier: Programming Language :: Python :: 3.4
